setup.py
scrolldown/__init__.py
scrolldown.egg-info/PKG-INFO
scrolldown.egg-info/SOURCES.txt
scrolldown.egg-info/dependency_links.txt
scrolldown.egg-info/top_level.txt